__init__.py
salt/__init__.py
salt/cli.py
salt/settings.py
salt/backend/__init__.py
salt/backend/scheduler/__init__.py
salt/backend/scheduler/scheduler.py
salt/backend/worker/__init__.py
salt/backend/worker/settings.py
salt/backend/worker/workflow_worker.py
salt/backend/workflow_service/__init__.py
salt/backend/workflow_service/utils.py
salt/backend/workflow_service/workflow_pb2.py
salt/backend/workflow_service/workflow_pb2.pyi
salt/backend/workflow_service/workflow_pb2_grpc.py
salt/backend/workflow_service/workflow_registry.py
salt/backend/workflow_service/workflow_service.py
salt/builders/__init__.py
salt/builders/py_builder.py
salt/framework/__init__.py
salt/framework/task.py
salt/framework/workflow.py
salt/utils/__init__.py
salt/utils/grpc/__init__.py
salt/utils/grpc/codegen.py
salt_py-0.1.0.dist-info/licenses/LICENSE
salt_py-0.1.0.dist-info/METADATA
salt_py-0.1.0.dist-info/WHEEL
salt_py-0.1.0.dist-info/entry_points.txt
salt_py-0.1.0.dist-info/top_level.txt
salt_py-0.1.0.dist-info/RECORD
