Metadata-Version: 2.4
Name: salt-py
Version: 0.1.0
Author-email: ginwakeup <iacopoantonelli@gmail.com>
License: MIT
Requires-Python: <3.11
License-File: LICENSE
Requires-Dist: typer>=0.16.0
Requires-Dist: toml>=0.10.2
Requires-Dist: pex>=2.46.2
Requires-Dist: setuptools>=80.9.0
Requires-Dist: loguru<1.0
Requires-Dist: redis<7.0
Requires-Dist: build<2.0
Requires-Dist: grpcio-tools
Requires-Dist: boto3
Requires-Dist: PyYaml
Requires-Dist: apscheduler
Requires-Dist: pydantic_settings
Requires-Dist: pika<2
Requires-Dist: docker
Provides-Extra: dev
Requires-Dist: pytest>=8.4.1; extra == "dev"
Requires-Dist: grpcio-tools; extra == "dev"
Dynamic: license-file
